neurotic/__init__.py
neurotic/__main__.py
neurotic/_elephant_tools.py
neurotic/global_config_template.txt
neurotic/scripts.py
neurotic/version.py
neurotic/datasets/__init__.py
neurotic/datasets/data.py
neurotic/datasets/download.py
neurotic/datasets/ftpauth.py
neurotic/datasets/gdrive.py
neurotic/datasets/metadata.py
neurotic/example/example-notebook.ipynb
neurotic/example/metadata.yml
neurotic/gui/__init__.py
neurotic/gui/config.py
neurotic/gui/epochencoder.py
neurotic/gui/notebook.py
neurotic/gui/standalone.py
neurotic/gui/icons/__init__.py
neurotic/gui/icons/icons.py
neurotic/gui/icons/make_resources.py
neurotic/tests/__init__.py
neurotic/tests/metadata-for-tests.yml
neurotic/tests/test_cli.py
neurotic/tests/test_examples.py
neurotic/tests/test_gui.py
neurotic/tests/test_neo_io.py
neurotic/tests/test_video_sync.py
neurotic-1.5.0.dist-info/LICENSE
neurotic-1.5.0.dist-info/METADATA
neurotic-1.5.0.dist-info/WHEEL
neurotic-1.5.0.dist-info/entry_points.txt
neurotic-1.5.0.dist-info/top_level.txt
neurotic-1.5.0.dist-info/RECORD
