Metadata-Version: 2.1
Name: neurotic
Version: 1.5.0
Summary: Curate, visualize, annotate, and share your behavioral ephys data using Python
Home-page: https://github.com/jpgill86/neurotic
Author: Jeffrey Gill
Author-email: jeffrey.p.gill@gmail.com
License: MIT
Project-URL: Documentation, https://neurotic.readthedocs.io
Project-URL: Source code, https://github.com/jpgill86/neurotic
Project-URL: Bug tracker, https://github.com/jpgill86/neurotic/issues
Project-URL: Change log, https://neurotic.readthedocs.io/en/latest/releasenotes.html
Keywords: neuroscience,electrophysiology,visualization,video-sync,data-management,data-sharing,download-manager,annotation-tool,open-science,python-neo
Platform: UNKNOWN
Classifier: Development Status :: 5 - Production/Stable
Classifier: Intended Audience :: Science/Research
Classifier: License :: OSI Approved :: MIT License
Classifier: Operating System :: OS Independent
Classifier: Programming Language :: Python :: 3
Classifier: Programming Language :: Python :: 3.6
Classifier: Programming Language :: Python :: 3.7
Classifier: Programming Language :: Python :: 3.8
Classifier: Programming Language :: Python :: 3.9
Classifier: Topic :: Scientific/Engineering
Requires-Dist: ephyviewer (>=1.3.0)
Requires-Dist: neo (>=0.7.2)
Requires-Dist: numpy
Requires-Dist: packaging
Requires-Dist: pandas
Requires-Dist: PyDrive2
Requires-Dist: pyqt5
Requires-Dist: pyyaml
Requires-Dist: quantities
Requires-Dist: requests
Requires-Dist: scipy
Requires-Dist: setuptools
Requires-Dist: toml
Requires-Dist: tqdm
Provides-Extra: docs
Requires-Dist: sphinx (<2) ; extra == 'docs'
Requires-Dist: readthedocs-sphinx-ext (<2.2) ; extra == 'docs'
Requires-Dist: sphinxcontrib-programoutput ; extra == 'docs'
Provides-Extra: notebook
Requires-Dist: ipython ; extra == 'notebook'
Requires-Dist: ipywidgets ; extra == 'notebook'
Provides-Extra: tests
Requires-Dist: coveralls ; extra == 'tests'
Requires-Dist: nose ; extra == 'tests'
